setup.py
Flask_ResponseExt.egg-info/PKG-INFO
Flask_ResponseExt.egg-info/SOURCES.txt
Flask_ResponseExt.egg-info/dependency_links.txt
Flask_ResponseExt.egg-info/not-zip-safe
Flask_ResponseExt.egg-info/requires.txt
Flask_ResponseExt.egg-info/top_level.txt
flask_responseext/__init__.py
flask_responseext/exceptions.py
flask_responseext/response.py
flask_responseext/status.py