Metadata-Version: 1.1
Name: Flask-ResponseExt
Version: 0.2.0
Summary: An extension of the Flask Response class.
Home-page: https://github.com/joelcolucci/flask-responseext
Author: Joel Colucci
Author-email: joelcolucci@gmail.com
License: MIT
Platform: any
Classifier: Environment :: Web Environment
Classifier: Intended Audience :: Developers
Classifier: License :: OSI Approved :: MIT License
Classifier: Operating System :: OS Independent
Classifier: Programming Language :: Python
Classifier: Topic :: Internet :: WWW/HTTP :: Dynamic Content
Classifier: Topic :: Software Development :: Libraries :: Python Modules
